[
  {
    "url": "/rhn/ssm/index.do",
    "count": 411
  },
  {
    "url": "/rhn/systems/details/Overview.do",
    "count": 402
  },
  {
    "url": "/rhn/systems/SystemList.do",
    "count": 257
  },
  {
    "url": "/rhn/ssm/PackageUpgrade.do",
    "count": 231
  },
  {
    "url": "/rhn/systems/details/packages/Packages.do",
    "count": 163
  },
  {
    "url": "/rhn/YourRhn.do",
    "count": 135
  },
  {
    "url": "/rhn/systems/details/ErrataList.do",
    "count": 133
  },
  {
    "url": "/rhn/systems/ssm/ListSystems.do",
    "count": 130
  },
  {
    "url": "/rhn/schedule/InProgressSystems.do",
    "count": 120
  },
  {
    "url": "/rhn/schedule/PendingActions.do",
    "count": 119
  },
  {
    "url": "/rhn/systems/ssm/ListErrata.do",
    "count": 109
  },
  {
    "url": "/rhn/systems/Search.do",
    "count": 105
  },
  {
    "url": "/rhn/systems/details/SPMigration.do",
    "count": 88
  },
  {
    "url": "/rhn/systems/ssm/misc/RebootSystem.do",
    "count": 86
  },
  {
    "url": "/rhn/ssm/ViewLog.do",
    "count": 81
  },
  {
    "url": "/rhn/schedule/ActionDetails.do",
    "count": 78
  },
  {
    "url": "/rhn/schedule/FailedSystems.do",
    "count": 70
  },
  {
    "url": "/rhn/systems/Overview.do",
    "count": 68
  },
  {
    "url": "/rhn/groups/ListRemoveSystems.do",
    "count": 63
  },
  {
    "url": "/rhn/systems/details/history/Event.do",
    "count": 57
  },
  {
    "url": "/rhn/systems/ssm/misc/RebootSystemConfirm.do",
    "count": 55
  },
  {
    "url": "/rhn/schedule/CompletedSystems.do",
    "count": 54
  },
  {
    "url": "/rhn/groups/GroupDetail.do",
    "count": 53
  },
  {
    "url": "/rhn/systems/SystemGroupList.do",
    "count": 52
  },
  {
    "url": "/rhn/manager/systems/details/highstate",
    "count": 46
  },
  {
    "url": "/rhn/schedule/FailedActions.do",
    "count": 45
  },
  {
    "url": "/rhn/schedule/CompletedActions.do",
    "count": 44
  },
  {
    "url": "/rhn/channel/ssm/ChannelSubscriptions.do",
    "count": 40
  },
  {
    "url": "/rhn/systems/Inactive.do",
    "count": 40
  },
  {
    "url": "/rhn/systems/details/packages/Packages.do",
    "count": 39
  },
  {
    "url": "/rhn/systems/details/history/Pending.do",
    "count": 38
  },
  {
    "url": "/rhn/systems/details/SystemChannels.do",
    "count": 38
  },
  {
    "url": "/rhn/systems/ssm/misc/Index.do",
    "count": 37
  },
  {
    "url": "/rhn/ssm/ViewAllLog.do",
    "count": 37
  },
  {
    "url": "/rhn/manager/systems/ssm/highstate",
    "count": 36
  },
  {
    "url": "/rhn/systems/details/packages/UpgradableList.do",
    "count": 34
  },
  {
    "url": "/rhn/manager/systems/keys",
    "count": 33
  },
  {
    "url": "/rhn/manager/systems/details/packages",
    "count": 32
  },
  {
    "url": "/rhn/systems/ssm/DeleteConfirm.do",
    "count": 31
  },
  {
    "url": "/rhn/systems/details/history/History.do",
    "count": 29
  },
  {
    "url": "/rhn/channels/ChannelSubscribers.do",
    "count": 28
  },
  {
    "url": "/rhn/systems/details/Overview.do",
    "count": 27
  },
  {
    "url": "/rhn/software/channels/Vendor.do",
    "count": 26
  },
  {
    "url": "/rhn/systems/SystemList.do",
    "count": 26
  },
  {
    "url": "/rhn/channels/ChannelDetail.do",
    "count": 25
  },
  {
    "url": "/rhn/ssm/Packages.do",
    "count": 25
  },
  {
    "url": "/rhn/systems/ssm/ListErrataConfirm.do",
    "count": 25
  },
  {
    "url": "/rhn/errata/details/Details.do",
    "count": 24
  },
  {
    "url": "/rhn/activationkeys/Edit.do",
    "count": 24
  },
  {
    "url": "/rhn/channels/software/Search.do",
    "count": 23
  },
  {
    "url": "/rhn/systems/details/DeleteConfirm.do",
    "count": 22
  },
  {
    "url": "/rhn/systems/details/ErrataList.do",
    "count": 22
  },
  {
    "url": "/rhn/systems/ssm/groups/Manage.do",
    "count": 21
  },
  {
    "url": "/rhn/ssm/PackageList.do",
    "count": 19
  },
  {
    "url": "/rhn/activationkeys/List.do",
    "count": 18
  },
  {
    "url": "/rhn/manager/admin/setup/products",
    "count": 17
  },
  {
    "url": "/rhn/systems/details/packages/InstallPackages.do",
    "count": 15
  },
  {
    "url": "/rhn/systems/RequiringReboot.do",
    "count": 14
  },
  {
    "url": "/rhn/systems/details/SystemHardware.do",
    "count": 14
  },
  {
    "url": "/rhn/systems/details/packages/PackageList.do",
    "count": 14
  },
  {
    "url": "/rhn/errata/details/Packages.do",
    "count": 13
  },
  {
    "url": "/rhn/systems/Ungrouped.do",
    "count": 12
  },
  {
    "url": "/rhn/systems/details/ErrataConfirm.do",
    "count": 12
  },
  {
    "url": "/rhn/ssm/ViewCompletedLog.do",
    "count": 12
  },
  {
    "url": "/rhn/activationkeys/systems/List.do",
    "count": 11
  },
  {
    "url": "/rhn/systems/details/Edit.do",
    "count": 11
  },
  {
    "url": "/rhn/admin/setup/ProxySettings.do",
    "count": 11
  },
  {
    "url": "/rhn/systems/details/virtualization/VirtualGuestsList.do",
    "count": 10
  },
  {
    "url": "/rhn/systems/details/SystemHardware.do",
    "count": 10
  },
  {
    "url": "/rhn/software/manage/packages/PackageList.do",
    "count": 10
  },
  {
    "url": "/rhn/channels/ChannelPackages.do",
    "count": 10
  },
  {
    "url": "/rhn/software/packages/NameOverview.do",
    "count": 10
  },
  {
    "url": "/rhn/groups/ListErrata.do",
    "count": 9
  },
  {
    "url": "/rhn/admin/setup/MirrorCredentials.do",
    "count": 9
  },
  {
    "url": "/rhn/ssm/PackageInstall.do",
    "count": 9
  },
  {
    "url": "/rhn/systems/details/packages/UpgradeConfirm.do",
    "count": 9
  },
  {
    "url": "/rhn/systems/ssm/groups/Confirm.do",
    "count": 9
  },
  {
    "url": "/rhn/systems/details/history/History.do",
    "count": 9
  },
  {
    "url": "/rhn/systems/details/history/Pending.do",
    "count": 9
  },
  {
    "url": "/rhn/software/channels/All.do",
    "count": 9
  },
  {
    "url": "/rhn/errata/details/Details.do",
    "count": 8
  },
  {
    "url": "/rhn/systems/details/packages/profiles/CompareSystems.do",
    "count": 8
  },
  {
    "url": "/rhn/activationkeys/packages/Packages.do",
    "count": 8
  },
  {
    "url": "/rhn/systems/details/history/Event.do",
    "count": 8
  },
  {
    "url": "/rhn/ssm/PackageRemove.do",
    "count": 7
  },
  {
    "url": "/rhn/channels/ChannelErrata.do",
    "count": 7
  },
  {
    "url": "/rhn/systems/details/packages/profiles/ShowProfiles.do",
    "count": 7
  },
  {
    "url": "/rhn/groups/GroupDetail.do",
    "count": 7
  },
  {
    "url": "/rhn/ssm/ViewLogDetails.do",
    "count": 7
  },
  {
    "url": "/rhn/users/UserDetails.do",
    "count": 7
  },
  {
    "url": "/rhn/errata/details/SystemsAffected.do",
    "count": 7
  },
  {
    "url": "/rhn/systems/details/packages/InstallConfirm.do",
    "count": 6
  },
  {
    "url": "/rhn/systems/details/SystemRemoteCommand.do",
    "count": 6
  },
  {
    "url": "/rhn/systems/details/history/FailEventConfirmation.do",
    "count": 6
  },
  {
    "url": "/rhn/account/UserDetails.do",
    "count": 6
  },
  {
    "url": "/rhn/YourRhn.do",
    "count": 6
  },
  {
    "url": "/rhn/schedule/PendingActionsDeleteConfirm.do",
    "count": 6
  },
  {
    "url": "/rhn/groups/ListRemoveSystems.do",
    "count": 5
  },
  {
    "url": "/rhn/systems/details/packages/PackageList.do",
    "count": 5
  },
  {
    "url": "/rhn/channels/manage/Manage.do",
    "count": 5
  },
  {
    "url": "/rhn/schedule/PackageList.do",
    "count": 5
  },
  {
    "url": "/rhn/systems/ssm/config/Deploy.do",
    "count": 5
  },
  {
    "url": "/rhn/systems/SystemGroupList.do",
    "count": 5
  },
  {
    "url": "/rhn/channels/manage/Delete.do",
    "count": 5
  },
  {
    "url": "/rhn/channels/manage/repos/RepoList.do",
    "count": 4
  },
  {
    "url": "/rhn/errata/details/Packages.do",
    "count": 4
  },
  {
    "url": "/rhn/channels/manage/Edit.do",
    "count": 4
  },
  {
    "url": "/rhn/software/channels/Custom.do",
    "count": 4
  },
  {
    "url": "/rhn/systems/details/groups/ListRemove.do",
    "count": 4
  },
  {
    "url": "/rhn/software/packages/Details.do",
    "count": 4
  },
  {
    "url": "/rhn/account/UserPreferences.do",
    "count": 4
  },
  {
    "url": "/rhn/activationkeys/groups/List.do",
    "count": 4
  },
  {
    "url": "/rhn/systems/details/packages/profiles/SyncSystems.do",
    "count": 4
  },
  {
    "url": "/rhn/users/ActiveList.do",
    "count": 4
  },
  {
    "url": "/rhn/channels/manage/repos/RepoEdit.do",
    "count": 4
  },
  {
    "url": "/rhn/systems/details/packages/RemoveConfirm.do",
    "count": 4
  },
  {
    "url": "/rhn/systems/ssm/provisioning/PowerManagementConfiguration.do",
    "count": 4
  },
  {
    "url": "/rhn/systems/OutOfDate.do",
    "count": 3
  },
  {
    "url": "/rhn/systems/details/packages/profiles/MissingPackageSubmit.do",
    "count": 3
  },
  {
    "url": "/rhn/software/packages/TargetSystems.do",
    "count": 3
  },
  {
    "url": "/rhn/channels/Managers.do",
    "count": 3
  },
  {
    "url": "/rhn/users/DeleteUser.do",
    "count": 3
  },
  {
    "url": "/rhn/systems/details/configuration/Overview.do",
    "count": 3
  },
  {
    "url": "/rhn/systems/details/audit/ListScap.do",
    "count": 3
  },
  {
    "url": "/rhn/ssm/ViewLog.do#",
    "count": 3
  },
  {
    "url": "/rhn/systems/details/ErrataConfirm.do",
    "count": 3
  },
  {
    "url": "/rhn/admin/multiorg/Users.do",
    "count": 3
  },
  {
    "url": "/rhn/groups/AdminList.do",
    "count": 3
  },
  {
    "url": "/rhn/systems/details/packages/profiles/MissingPackages.do",
    "count": 3
  },
  {
    "url": "/rhn/systems/details/RebootSystem.do",
    "count": 3
  },
  {
    "url": "/rhn/systems/details/history/PendingDelete.do",
    "count": 3
  },
  {
    "url": "/rhn/systems/ssm/config/Subscribe.do",
    "count": 3
  },
  {
    "url": "/rhn/admin/config/BootstrapConfig.do",
    "count": 2
  },
  {
    "url": "/rhn/errata/RelevantErrata.do",
    "count": 2
  },
  {
    "url": "/rhn/software/manage/packages/ConfirmPackageRemove.do",
    "count": 2
  },
  {
    "url": "/rhn/users/UserList.do",
    "count": 2
  },
  {
    "url": "/rhn/manager/cm/imagestores/create",
    "count": 2
  },
  {
    "url": "/rhn/systems/details/history/FailEventConfirmation.do",
    "count": 2
  },
  {
    "url": "/rhn/manager/cm/images",
    "count": 2
  },
  {
    "url": "/rhn/channels/software/Search.do",
    "count": 2
  },
  {
    "url": "/rhn/activationkeys/Edit.do",
    "count": 2
  },
  {
    "url": "/rhn/activationkeys/configuration/List.do",
    "count": 2
  },
  {
    "url": "/rhn/activationkeys/List.do",
    "count": 2
  },
  {
    "url": "/rhn/channels/TargetSystems.do",
    "count": 2
  },
  {
    "url": "/rhn/admin/Catalina.do",
    "count": 2
  },
  {
    "url": "/rhn/errata/AllErrata.do",
    "count": 2
  },
  {
    "url": "/rhn/admin/multiorg/Organizations.do",
    "count": 2
  },
  {
    "url": "/rhn/systems/PhysicalList.do",
    "count": 2
  },
  {
    "url": "/rhn/systems/ssm/MigrateSystems.do",
    "count": 2
  },
  {
    "url": "/rhn/systems/ssm/ErrataSystemsAffected.do",
    "count": 2
  },
  {
    "url": "/rhn/software/packages/ChangeLog.do",
    "count": 2
  },
  {
    "url": "/rhn/YourRhn.do#",
    "count": 2
  },
  {
    "url": "/rhn/systems/Ungrouped.do",
    "count": 2
  },
  {
    "url": "/rhn/schedule/ActionDetails.do",
    "count": 2
  },
  {
    "url": "/rhn/systems/details/kickstart/PowerManagement.do",
    "count": 2
  },
  {
    "url": "/rhn/systems/Registered.do",
    "count": 2
  },
  {
    "url": "/rhn/admin/config/BootstrapSystems.do",
    "count": 2
  },
  {
    "url": "/rhn/admin/config/Cobbler.do",
    "count": 2
  },
  {
    "url": "/rhn/admin/config/GeneralConfig.do",
    "count": 2
  },
  {
    "url": "/rhn/systems/details/audit/ScheduleXccdf.do",
    "count": 1
  },
  {
    "url": "/pub/repositories/sle/12/4/",
    "count": 1
  },
  {
    "url": "/rhn/users/DeleteUserSubmit.do",
    "count": 1
  },
  {
    "url": "/rhn/systems/VirtualList.do",
    "count": 1
  },
  {
    "url": "/rhn/admin/config/Orgs.do",
    "count": 1
  },
  {
    "url": "/rhn/admin/config/Restart.do",
    "count": 1
  },
  {
    "url": "/rhn/admin/multiorg/OrgDetails.do",
    "count": 1
  },
  {
    "url": "/rhn/manager/multiorg/details/custom",
    "count": 1
  },
  {
    "url": "/rhn/admin/multiorg/OrgUsers.do",
    "count": 1
  },
  {
    "url": "/rhn/users/CreateUser.do",
    "count": 1
  },
  {
    "url": "/rhn/channels/manage/DistChannelMap.do",
    "count": 1
  },
  {
    "url": "/rhn/software/channels/Retired.do",
    "count": 1
  },
  {
    "url": "/rhn/groups/SystemsAffected.do",
    "count": 1
  },
  {
    "url": "/rhn/systems/Inactive.do",
    "count": 1
  },
  {
    "url": "/rhn/multiorg/OrgConfigDetails.do",
    "count": 1
  },
  {
    "url": "/rhn/systems/ssm/misc/SoftwareRefresh.do",
    "count": 1
  },
  {
    "url": "/rhn/manager/systems/details/formulas",
    "count": 1
  },
  {
    "url": "/rhn/systems/Overview.do",
    "count": 1
  },
  {
    "url": "/rhn/systems/ssm/config/Rank.do",
    "count": 1
  },
  {
    "url": "/rhn/systems/ssm/config/SubscribeConfirm.do",
    "count": 1
  },
  {
    "url": "/rhn/activationkeys/systems/List.do",
    "count": 1
  },
  {
    "url": "/rhn/ssm/index.do",
    "count": 1
  },
  {
    "url": "/rhn/manager/notification-messages",
    "count": 1
  },
  {
    "url": "/rhn/systems/BootstrapSystemList.do",
    "count": 1
  },
  {
    "url": "/pub/repositories/sle/12/4/bootstrap/repodata/",
    "count": 1
  },
  {
    "url": "/rhn/systems/ssm/config/Diff.do",
    "count": 1
  },
  {
    "url": "/rhn/software/packages/NameOverview.do",
    "count": 1
  },
  {
    "url": "/rhn/systems/details/packages/InstallPackages.do",
    "count": 1
  },
  {
    "url": "/rhn/systems/Search.do",
    "count": 1
  },
  {
    "url": "/pub/repositories/sle/12/4/bootstrap/",
    "count": 1
  },
  {
    "url": "/rhn/errata/details/ErrataConfirm.do",
    "count": 1
  },
  {
    "url": "/rhn/manager/cm/import",
    "count": 1
  },
  {
    "url": "/rhn/activationkeys/groups/Add.do",
    "count": 1
  },
  {
    "url": "/pub/repositories/sle/12/4/bootstrap/repodata/repomd.xml",
    "count": 1
  },
  {
    "url": "/rhn/manager/cm/build",
    "count": 1
  },
  {
    "url": "/rhn/manager/cm/imagestores",
    "count": 1
  },
  {
    "url": "/rhn/systems/details/ListCustomData.do",
    "count": 1
  },
  {
    "url": "/rhn/systems/details/audit/ListScap.do",
    "count": 1
  },
  {
    "url": "/rhn/systems/details/configuration/DiffFileConfirm.do",
    "count": 1
  },
  {
    "url": "/rhn/manager/systems/details/custom",
    "count": 1
  },
  {
    "url": "/rhn/software/packages/ChangeLog.do",
    "count": 1
  },
  {
    "url": "/rhn/schedule/CompletedSystems.do",
    "count": 1
  },
  {
    "url": "/rhn/software/packages/InstalledSystems.do",
    "count": 1
  },
  {
    "url": "/rhn/systems/DuplicateIPList.do",
    "count": 1
  },
  {
    "url": "/rhn/channels/manage/ChannelPackages.do",
    "count": 1
  },
  {
    "url": "/rhn/systems/details/Edit.do",
    "count": 1
  },
  {
    "url": "/rhn/systems/ssm/ListSystems.do",
    "count": 1
  },
  {
    "url": "/rhn/schedule/InProgressSystems.do",
    "count": 1
  },
  {
    "url": "/rhn/systems/details/packages/profiles/SyncSystemsSubmit.do",
    "count": 1
  }
]